Metadata-Version: 2.1
Name: wavenet-vocoder
Version: 0.1.1
Summary: PyTorch implementation of WaveNet vocoder
Home-page: UNKNOWN
License: UNKNOWN
Platform: UNKNOWN
Provides-Extra: test
Provides-Extra: train
